{
    "tsys_symbols": {
        "id": {
            "_name": "id"
            , "_label": "ID"
            , "_type": "number"
            , "_visible": false
            , "_required": false
            , "_editable": false
            , "_message": ""
        },
        "name" :{
            "_name": "name"
            , "_label": "Name"
            , "_type": "text"
            , "_visible": true
            , "_required": true
            , "_editable": true
            , "_message": "Provide a name to your unit"
            , "_props": {
                "minLength": 3,
                "maxLength": 20
            }
        }
        , "abbreviation" : {
            "_name": "abbreviation"
            , "_label": "Abbreviation"
            , "_type": "text"
            , "_visible": true
            , "_required": true
            , "_editable": true
            , "_message": "Type an abbreviation of the name"
            , "_props": {
                "minLength": 1,
                "maxLength": 5
            }
        }
        , "base" : {
            "_name": "base"
            , "_label": "Base"
            , "_type": "number"
            , "_visible": true
            , "_required": true
            , "_editable": true
            , "_message": "A base value is required to calculate conversions"
            , "_props": {
                "min": 1
            }
        }
        , "type": {
            "_name": "type"
            , "_label": "Type"
            , "_type": "select"
            , "_visible": true
            , "_required": true
            , "_editable": true
            , "_message": "Select a category for this unit"
        }
        , "created_by": {
            "_name": "created_by"
            , "_label": "Created By"
            , "_type": "text"
            , "_visible": true
            , "_required": false
            , "_editable": false
            , "_message": ""
            , "_props": {
                "crud": {
                    "visible": {
                        "create": false
                        , "update": true
                        , "read": true
                    }
                }
            }
        }
    }
}